ztffields/__init__.py
ztffields/fields.py
ztffields/io.py
ztffields/plotting.py
ztffields/projection.py
ztffields/utils.py
ztffields/data/ztf_ccd_layout.tbl
ztffields/data/ztf_ccd_quad_layout.tbl
ztffields/data/ztf_fields.txt
ztffields-0.6.1.dist-info/LICENSE
ztffields-0.6.1.dist-info/METADATA
ztffields-0.6.1.dist-info/WHEEL
ztffields-0.6.1.dist-info/top_level.txt
ztffields-0.6.1.dist-info/RECORD
