Metadata-Version: 2.2
Name: ztffields
Version: 0.6.1
Summary: Access and Interact with ZTF Fields
Home-page: https://github.com/MickaelRigault/ztffields
Author: Mickael Rigault
Author-email: m.rigault@ipnl.in2p3.fr
License: Apache Software License
Keywords: astronomy,astrophysics
Classifier: Development Status :: 2 - Pre-Alpha
Classifier: Intended Audience :: Science/Research
Classifier: License :: OSI Approved :: Apache Software License
Classifier: Programming Language :: Python :: 3
Classifier: Topic :: Scientific/Engineering :: Astronomy
Classifier: Topic :: Scientific/Engineering :: Physics
Requires-Python: >=3.1
License-File: LICENSE
Requires-Dist: importlib_resources; python_version < "3.10"
Requires-Dist: numpy
Requires-Dist: matplotlib
Requires-Dist: pandas
Requires-Dist: shapely
Requires-Dist: geopandas
Provides-Extra: docs
Requires-Dist: nbsphinx; extra == "docs"
Provides-Extra: tests
Requires-Dist: pytest; extra == "tests"
Requires-Dist: coverage; extra == "tests"
